{
  "title": "The Harvard President Will See You Now",
  "date": "2015-09-03",
  "description": "<p>How a pain-in-the-neck girl from rural Virginia came to run the most powerful university in the world.</p><img src=\"http://feeds.feedburner.com/~r/freakonomicsradio/~4/gH8KzxnVEsc\" height=\"1\" width=\"1\" alt=\"\"/>",
  "episode_url": "http://feedproxy.google.com/~r/freakonomicsradio/~5/6X3ykLxtBU0/freakonomics_podcast090215.mp3",
  "segments": {
  },
  "slug": "The-Harvard-President-Will-See-You-Now"
}